{
	"game":{
		"buildings":[
			{
				"item":"CcCcCcCc",
				"pos":{
					"r":0,
					"x":-10,
					"y":9
				},
				"type":"emitter"
			},
			{
				"item":"RbRbRbRb",
				"pos":{
					"r":0,
					"x":-6,
					"y":9
				},
				"type":"emitter"
			},
			{
				"item":"RbCc--Cc:----Rb--",
				"pos":{
					"r":0,
					"x":9,
					"y":-10
				},
				"type":"goal"
			}
		],
		"bounds":{
			"w":20,
			"h":20
		},
		"version":1,
		"excludedBuildings":[]
	},
	"meta":{
		"downloads":8,
		"shortKey":"RbCc--Cc:----Rb--",
		"author":"gentryaustin",
		"completions":2,
		"id":1075,
		"completed":false,
		"title":"Logo_Blue_Edition",
		"likes":1
	}
}
