{
	"game":{
		"buildings":[
			{
				"item":"CuCuCuCu",
				"pos":{
					"r":0,
					"x":-3,
					"y":3
				},
				"type":"emitter"
			},
			{
				"item":"SuSuSuSu",
				"pos":{
					"r":0,
					"x":-2,
					"y":3
				},
				"type":"emitter"
			},
			{
				"item":"red",
				"pos":{
					"r":270,
					"x":3,
					"y":3
				},
				"type":"emitter"
			},
			{
				"item":"green",
				"pos":{
					"r":270,
					"x":3,
					"y":2
				},
				"type":"emitter"
			},
			{
				"item":"blue",
				"pos":{
					"r":270,
					"x":3,
					"y":1
				},
				"type":"emitter"
			},
			{
				"item":"CcSrCc--",
				"pos":{
					"r":90,
					"x":2,
					"y":-4
				},
				"type":"goal"
			},
			{
				"pos":{
					"r":0,
					"x":-5,
					"y":3
				},
				"type":"block"
			},
			{
				"pos":{
					"r":0,
					"x":-4,
					"y":3
				},
				"type":"block"
			},
			{
				"pos":{
					"r":0,
					"x":-1,
					"y":3
				},
				"type":"block"
			},
			{
				"pos":{
					"r":0,
					"x":3,
					"y":0
				},
				"type":"block"
			},
			{
				"pos":{
					"r":0,
					"x":3,
					"y":-1
				},
				"type":"block"
			},
			{
				"pos":{
					"r":0,
					"x":3,
					"y":-2
				},
				"type":"block"
			},
			{
				"pos":{
					"r":0,
					"x":3,
					"y":-3
				},
				"type":"block"
			},
			{
				"pos":{
					"r":0,
					"x":3,
					"y":-4
				},
				"type":"block"
			},
			{
				"pos":{
					"r":0,
					"x":3,
					"y":-5
				},
				"type":"block"
			},
			{
				"pos":{
					"r":0,
					"x":2,
					"y":-5
				},
				"type":"block"
			},
			{
				"pos":{
					"r":0,
					"x":2,
					"y":-3
				},
				"type":"block"
			},
			{
				"pos":{
					"r":0,
					"x":2,
					"y":-2
				},
				"type":"block"
			},
			{
				"pos":{
					"r":0,
					"x":2,
					"y":-1
				},
				"type":"block"
			},
			{
				"pos":{
					"r":0,
					"x":2,
					"y":0
				},
				"type":"block"
			}
		],
		"bounds":{
			"w":9,
			"h":9
		},
		"version":1
	},
	"meta":{
		"difficulty":0.3389830508474576,
		"averageTime":193.76923076923077,
		"downloads":59,
		"shortKey":"CcSrCc--",
		"author":"anonymous",
		"completions":39,
		"id":153,
		"completed":false,
		"title":"Fish or something",
		"likes":13
	}
}
