{
	"game":{
		"buildings":[
			{
				"item":"RuRuRuRu",
				"pos":{
					"r":90,
					"x":-4,
					"y":-3
				},
				"type":"emitter"
			},
			{
				"item":"RuRu----",
				"pos":{
					"r":90,
					"x":3,
					"y":2
				},
				"type":"goal"
			}
		],
		"bounds":{
			"w":8,
			"h":6
		},
		"version":1,
		"excludedBuildings":[
			"rotater",
			"stacker",
			"mixer",
			"painter",
			"underground_belt"
		]
	},
	"meta":{
		"difficulty":0.2222222222222222,
		"averageTime":15.5,
		"downloads":18,
		"shortKey":"RuRu----:RrRcRwRg",
		"author":"kubagames143",
		"completions":14,
		"id":1597,
		"completed":false,
		"title":"8x6 Freeform Lvl 4",
		"likes":0
	}
}
