{
	"game":{
		"buildings":[
			{
				"pos":{
					"r":0,
					"x":-2,
					"y":-2
				},
				"type":"block"
			},
			{
				"pos":{
					"r":0,
					"x":-1,
					"y":-2
				},
				"type":"block"
			},
			{
				"pos":{
					"r":0,
					"x":0,
					"y":-2
				},
				"type":"block"
			},
			{
				"pos":{
					"r":0,
					"x":-2,
					"y":1
				},
				"type":"block"
			},
			{
				"pos":{
					"r":0,
					"x":-1,
					"y":1
				},
				"type":"block"
			},
			{
				"pos":{
					"r":0,
					"x":0,
					"y":1
				},
				"type":"block"
			},
			{
				"pos":{
					"r":0,
					"x":-1,
					"y":0
				},
				"type":"block"
			},
			{
				"item":"green",
				"pos":{
					"r":0,
					"x":-2,
					"y":0
				},
				"type":"emitter"
			},
			{
				"item":"green",
				"pos":{
					"r":0,
					"x":0,
					"y":0
				},
				"type":"emitter"
			},
			{
				"item":"CuCuCuCu",
				"pos":{
					"r":0,
					"x":-5,
					"y":1
				},
				"type":"emitter"
			},
			{
				"item":"RuRuRuRu",
				"pos":{
					"r":0,
					"x":3,
					"y":1
				},
				"type":"emitter"
			},
			{
				"item":"CgCgCgCg",
				"pos":{
					"r":0,
					"x":-5,
					"y":-2
				},
				"type":"goal"
			},
			{
				"item":"RgRgRgRg",
				"pos":{
					"r":180,
					"x":1,
					"y":0
				},
				"type":"goal"
			}
		],
		"bounds":{
			"w":9,
			"h":4
		},
		"version":1,
		"excludedBuildings":[
			"balancer",
			"cutter",
			"rotater",
			"stacker",
			"mixer",
			"trash"
		]
	},
	"meta":{
		"difficulty":0.1273445212240869,
		"averageTime":130.0656108597285,
		"downloads":1015,
		"shortKey":"CgRgCgRg",
		"author":"kavirnyadeltoid",
		"completions":884,
		"id":2027,
		"completed":true,
		"title":"Catch example 1",
		"likes":320
	}
}
