{
	"game":{
		"buildings":[
			{
				"pos":{
					"r":0,
					"x":-3,
					"y":-1
				},
				"type":"block"
			},
			{
				"pos":{
					"r":0,
					"x":1,
					"y":0
				},
				"type":"block"
			},
			{
				"pos":{
					"r":0,
					"x":1,
					"y":-1
				},
				"type":"block"
			},
			{
				"item":"--Cp----:--Cb----:--Cg----",
				"pos":{
					"r":270,
					"x":-3,
					"y":-3
				},
				"type":"goal"
			},
			{
				"item":"Cg--CpCb",
				"pos":{
					"r":270,
					"x":1,
					"y":2
				},
				"type":"emitter"
			},
			{
				"pos":{
					"r":0,
					"x":-3,
					"y":0
				},
				"type":"block"
			}
		],
		"bounds":{
			"w":5,
			"h":6
		},
		"version":1,
		"excludedBuildings":[
			"mixer",
			"painter"
		]
	},
	"meta":{
		"difficulty":0.31818181818181823,
		"averageTime":94.66666666666667,
		"downloads":22,
		"shortKey":"--Cp----:--Cb----:--Cg----",
		"author":"mootmoot",
		"completions":15,
		"id":2187,
		"completed":true,
		"title":"3 to 1",
		"likes":4
	}
}
