{
	"game":{
		"buildings":[
			{
				"item":"RyRyRyRy",
				"pos":{
					"r":0,
					"x":2,
					"y":-2
				},
				"type":"goal"
			},
			{
				"item":"WuWuWuWu",
				"pos":{
					"r":0,
					"x":3,
					"y":0
				},
				"type":"emitter"
			},
			{
				"item":"WuWuWuWu",
				"pos":{
					"r":0,
					"x":3,
					"y":-2
				},
				"type":"goal"
			},
			{
				"item":"CpCpCpCp",
				"pos":{
					"r":90,
					"x":0,
					"y":-1
				},
				"type":"goal"
			},
			{
				"item":"CrCrCrCr",
				"pos":{
					"r":270,
					"x":-4,
					"y":-1
				},
				"type":"goal"
			},
			{
				"item":"CrCrCrCr",
				"pos":{
					"r":90,
					"x":-4,
					"y":-2
				},
				"type":"emitter"
			},
			{
				"item":"ScScScSc",
				"pos":{
					"r":180,
					"x":-2,
					"y":-2
				},
				"type":"emitter"
			},
			{
				"item":"ScScScSc",
				"pos":{
					"r":180,
					"x":-2,
					"y":-1
				},
				"type":"goal"
			},
			{
				"item":"CpCpCpCp",
				"pos":{
					"r":0,
					"x":1,
					"y":-1
				},
				"type":"emitter"
			},
			{
				"item":"RyRyRyRy",
				"pos":{
					"r":90,
					"x":-4,
					"y":0
				},
				"type":"emitter"
			},
			{
				"pos":{
					"r":0,
					"x":-5,
					"y":-3
				},
				"type":"block"
			},
			{
				"pos":{
					"r":0,
					"x":-4,
					"y":-3
				},
				"type":"block"
			},
			{
				"pos":{
					"r":0,
					"x":-3,
					"y":-3
				},
				"type":"block"
			},
			{
				"pos":{
					"r":0,
					"x":-2,
					"y":-3
				},
				"type":"block"
			},
			{
				"pos":{
					"r":0,
					"x":-1,
					"y":-3
				},
				"type":"block"
			},
			{
				"pos":{
					"r":0,
					"x":0,
					"y":-3
				},
				"type":"block"
			},
			{
				"pos":{
					"r":0,
					"x":1,
					"y":-3
				},
				"type":"block"
			},
			{
				"pos":{
					"r":0,
					"x":2,
					"y":-3
				},
				"type":"block"
			},
			{
				"pos":{
					"r":0,
					"x":3,
					"y":-3
				},
				"type":"block"
			},
			{
				"pos":{
					"r":0,
					"x":4,
					"y":-3
				},
				"type":"block"
			},
			{
				"pos":{
					"r":0,
					"x":4,
					"y":-2
				},
				"type":"block"
			},
			{
				"pos":{
					"r":0,
					"x":4,
					"y":-1
				},
				"type":"block"
			},
			{
				"pos":{
					"r":0,
					"x":4,
					"y":0
				},
				"type":"block"
			},
			{
				"pos":{
					"r":0,
					"x":4,
					"y":1
				},
				"type":"block"
			},
			{
				"pos":{
					"r":0,
					"x":3,
					"y":1
				},
				"type":"block"
			},
			{
				"pos":{
					"r":0,
					"x":2,
					"y":1
				},
				"type":"block"
			},
			{
				"pos":{
					"r":0,
					"x":1,
					"y":1
				},
				"type":"block"
			},
			{
				"pos":{
					"r":0,
					"x":0,
					"y":1
				},
				"type":"block"
			},
			{
				"pos":{
					"r":0,
					"x":-1,
					"y":1
				},
				"type":"block"
			},
			{
				"pos":{
					"r":0,
					"x":-2,
					"y":1
				},
				"type":"block"
			},
			{
				"pos":{
					"r":0,
					"x":-3,
					"y":1
				},
				"type":"block"
			},
			{
				"pos":{
					"r":0,
					"x":-4,
					"y":1
				},
				"type":"block"
			},
			{
				"pos":{
					"r":0,
					"x":-5,
					"y":1
				},
				"type":"block"
			},
			{
				"pos":{
					"r":0,
					"x":-5,
					"y":0
				},
				"type":"block"
			},
			{
				"pos":{
					"r":0,
					"x":-5,
					"y":-1
				},
				"type":"block"
			},
			{
				"pos":{
					"r":0,
					"x":-5,
					"y":-2
				},
				"type":"block"
			}
		],
		"bounds":{
			"w":10,
			"h":5
		},
		"version":1,
		"excludedBuildings":[]
	},
	"meta":{
		"difficulty":0.1875,
		"averageTime":12.23076923076923,
		"downloads":16,
		"shortKey":"SrWrSrWr:SwRwSwRw",
		"author":"BlueSynopsis",
		"completions":13,
		"id":2254,
		"completed":false,
		"title":"11 - Mix And Match",
		"likes":3
	}
}
