{
	"game":{
		"buildings":[
			{
				"item":"--Cp--Cp:----Sb--:----Cg--:--Rg--Rc",
				"pos":{
					"r":90,
					"x":-8,
					"y":7
				},
				"type":"emitter"
			},
			{
				"item":"--Cp--Cp:----Sb--:----Cg--:--Rg--Rc",
				"pos":{
					"r":0,
					"x":-5,
					"y":6
				},
				"type":"goal"
			},
			{
				"item":"--Cy--Cy:----Sb--:----Cg--:--Rg--Rg",
				"pos":{
					"r":270,
					"x":-8,
					"y":6
				},
				"type":"goal"
			},
			{
				"item":"--Cy--Cy:----Sb--:----Cg--:--Rg--Rg",
				"pos":{
					"r":180,
					"x":-6,
					"y":6
				},
				"type":"goal"
			},
			{
				"item":"--Cy--Cy:----Sb--:----Cg--:--Rg--Rg",
				"pos":{
					"r":270,
					"x":-5,
					"y":5
				},
				"type":"emitter"
			},
			{
				"item":"--Cy--Cy:----Sb--:----Cg--:--Rg--Rg",
				"pos":{
					"r":90,
					"x":8,
					"y":8
				},
				"type":"goal"
			},
			{
				"item":"--Cb--Cb:----Sb--:----Cg--:--Rg--Rc",
				"pos":{
					"r":90,
					"x":-8,
					"y":3
				},
				"type":"emitter"
			},
			{
				"item":"--Cw--Cw:----Sb--:----Cg--:--Rg--Rc",
				"pos":{
					"r":90,
					"x":-7,
					"y":1
				},
				"type":"emitter"
			},
			{
				"item":"--Cy--Cy:----Sb--",
				"pos":{
					"r":0,
					"x":-3,
					"y":0
				},
				"type":"emitter"
			},
			{
				"item":"--Cw--Cw:----Sb--:----Cg--:--Rg--Rc",
				"pos":{
					"r":270,
					"x":-3,
					"y":1
				},
				"type":"goal"
			},
			{
				"item":"--Cb--Cb:----Sb--:----Cg--:--Rg--Rc",
				"pos":{
					"r":270,
					"x":-8,
					"y":-2
				},
				"type":"goal"
			},
			{
				"item":"--Cc--Cc:----Sb--:----Cg--:--Rg--Rc",
				"pos":{
					"r":0,
					"x":-9,
					"y":-2
				},
				"type":"emitter"
			},
			{
				"item":"--Cr--Cr:----Sb--:----Cg--:--Rg--Rc",
				"pos":{
					"r":90,
					"x":-2,
					"y":4
				},
				"type":"emitter"
			},
			{
				"item":"--Cr--Cr:----Sb--:----Cg--:--Rg--Rc",
				"pos":{
					"r":270,
					"x":-2,
					"y":5
				},
				"type":"goal"
			},
			{
				"item":"--Cr--Cr:----Sb--:----Cg--:--Rg--Rc",
				"pos":{
					"r":90,
					"x":1,
					"y":5
				},
				"type":"goal"
			},
			{
				"item":"----Cg--:--Rc--Rg",
				"pos":{
					"r":0,
					"x":0,
					"y":-3
				},
				"type":"goal"
			},
			{
				"item":"--Cy--Cy:----Sb--:----Cg--:--Rc--Rg",
				"pos":{
					"r":0,
					"x":-10,
					"y":-4
				},
				"type":"goal"
			},
			{
				"item":"--Cp--Cp:----Sb--:----Cg--:--Rg--Rc",
				"pos":{
					"r":180,
					"x":2,
					"y":-2
				},
				"type":"emitter"
			},
			{
				"item":"--Cy--Cy:----Sb--:----Cg--:--Rc--Rc",
				"pos":{
					"r":180,
					"x":9,
					"y":6
				},
				"type":"goal"
			},
			{
				"item":"--Cy--Cy:----Sb--:----Cg--:--Rc--Rc",
				"pos":{
					"r":0,
					"x":-10,
					"y":-5
				},
				"type":"emitter"
			},
			{
				"item":"----Cg--:--Rc--Rg",
				"pos":{
					"r":0,
					"x":6,
					"y":-2
				},
				"type":"emitter"
			},
			{
				"item":"--Cy--Cy:----Sy--:----Cg--:--Rg--Rc",
				"pos":{
					"r":180,
					"x":5,
					"y":-2
				},
				"type":"goal"
			},
			{
				"item":"--Cy--Cy:----Sc--:----Cg--:--Rg--Rc",
				"pos":{
					"r":0,
					"x":5,
					"y":2
				},
				"type":"goal"
			},
			{
				"item":"--Cy--Cy:----Sc--:----Cg--:--Rg--Rc",
				"pos":{
					"r":270,
					"x":6,
					"y":-5
				},
				"type":"emitter"
			},
			{
				"item":"--Cp--Cp:----Sb--:----Cg--:--Rg--Rc",
				"pos":{
					"r":270,
					"x":6,
					"y":0
				},
				"type":"goal"
			},
			{
				"item":"--Cy--Cy:----Sb--:----Cg--:--Rc--Rg",
				"pos":{
					"r":270,
					"x":5,
					"y":-6
				},
				"type":"goal"
			},
			{
				"item":"--Cc--Cc:----Sb--:----Cg--:--Rg--Rc",
				"pos":{
					"r":180,
					"x":8,
					"y":-3
				},
				"type":"goal"
			},
			{
				"item":"--Cy--Cy:----Sg--:----Cg--:--Rg--Rc",
				"pos":{
					"r":270,
					"x":1,
					"y":-5
				},
				"type":"emitter"
			},
			{
				"item":"--Cy--Cy:----Sb--:----Cg--:--Rg--Rc",
				"pos":{
					"r":90,
					"x":1,
					"y":-4
				},
				"type":"goal"
			},
			{
				"item":"--Cy--Cy:----Sg--:----Cg--:--Rg--Rc",
				"pos":{
					"r":270,
					"x":-2,
					"y":-5
				},
				"type":"goal"
			},
			{
				"item":"--Cr--Cr:----Sb--:----Cg--:--Rg--Rc",
				"pos":{
					"r":270,
					"x":-2,
					"y":-6
				},
				"type":"goal"
			},
			{
				"item":"----Cg--:--Rg--Rc",
				"pos":{
					"r":180,
					"x":-6,
					"y":-6
				},
				"type":"emitter"
			},
			{
				"item":"--Cy--Cy:----Sy--:----Cg--:--Rg--Rc",
				"pos":{
					"r":180,
					"x":5,
					"y":-4
				},
				"type":"emitter"
			}
		],
		"bounds":{
			"w":20,
			"h":20
		},
		"version":1,
		"excludedBuildings":[
			"cutter",
			"rotater",
			"mixer",
			"painter",
			"underground_belt"
		]
	},
	"meta":{
		"downloads":14,
		"shortKey":"CrCpCpCr",
		"author":"897701215",
		"completions":2,
		"id":3171,
		"completed":true,
		"title":"confound with",
		"likes":2
	}
}
