{
	"game":{
		"buildings":[
			{
				"item":"CuCuCuCu",
				"pos":{
					"r":0,
					"x":-4,
					"y":2
				},
				"type":"emitter"
			},
			{
				"item":"red",
				"pos":{
					"r":0,
					"x":-3,
					"y":2
				},
				"type":"emitter"
			},
			{
				"pos":{
					"r":0,
					"x":-3,
					"y":0
				},
				"type":"block"
			},
			{
				"item":"CrCrCrCr",
				"pos":{
					"r":180,
					"x":1,
					"y":0
				},
				"type":"goal"
			},
			{
				"pos":{
					"r":0,
					"x":0,
					"y":0
				},
				"type":"block"
			},
			{
				"pos":{
					"r":0,
					"x":0,
					"y":1
				},
				"type":"block"
			},
			{
				"pos":{
					"r":0,
					"x":1,
					"y":1
				},
				"type":"block"
			},
			{
				"pos":{
					"r":0,
					"x":2,
					"y":1
				},
				"type":"block"
			},
			{
				"pos":{
					"r":0,
					"x":2,
					"y":0
				},
				"type":"block"
			},
			{
				"pos":{
					"r":0,
					"x":2,
					"y":-1
				},
				"type":"block"
			},
			{
				"pos":{
					"r":0,
					"x":2,
					"y":-2
				},
				"type":"block"
			},
			{
				"pos":{
					"r":0,
					"x":1,
					"y":-2
				},
				"type":"block"
			},
			{
				"pos":{
					"r":0,
					"x":0,
					"y":-2
				},
				"type":"block"
			},
			{
				"pos":{
					"r":0,
					"x":-1,
					"y":-2
				},
				"type":"block"
			},
			{
				"pos":{
					"r":0,
					"x":-2,
					"y":-2
				},
				"type":"block"
			},
			{
				"pos":{
					"r":0,
					"x":-3,
					"y":-2
				},
				"type":"block"
			},
			{
				"pos":{
					"r":0,
					"x":-2,
					"y":2
				},
				"type":"block"
			}
		],
		"bounds":{
			"w":8,
			"h":6
		},
		"version":1,
		"excludedBuildings":[
			"belt"
		]
	},
	"meta":{
		"difficulty":0.0803571428571429,
		"averageTime":66.02912621359224,
		"downloads":112,
		"shortKey":"CrCrCrCr:Cr------:CrCrCrCr:CrCrCrCr",
		"author":"rootysoda",
		"completions":103,
		"id":3936,
		"completed":false,
		"title":"no conveyors",
		"likes":24
	}
}
