{
	"game":{
		"buildings":[
			{
				"item":"CuCuCuCu",
				"pos":{
					"r":0,
					"x":-2,
					"y":5
				},
				"type":"emitter"
			},
			{
				"item":"red",
				"pos":{
					"r":90,
					"x":-2,
					"y":2
				},
				"type":"emitter"
			},
			{
				"item":"yellow",
				"pos":{
					"r":270,
					"x":1,
					"y":2
				},
				"type":"emitter"
			},
			{
				"item":"blue",
				"pos":{
					"r":270,
					"x":-1,
					"y":-1
				},
				"type":"emitter"
			},
			{
				"item":"green",
				"pos":{
					"r":90,
					"x":0,
					"y":-1
				},
				"type":"emitter"
			},
			{
				"pos":{
					"r":0,
					"x":-1,
					"y":0
				},
				"type":"block"
			},
			{
				"pos":{
					"r":0,
					"x":0,
					"y":0
				},
				"type":"block"
			},
			{
				"pos":{
					"r":0,
					"x":-1,
					"y":5
				},
				"type":"block"
			},
			{
				"pos":{
					"r":0,
					"x":1,
					"y":5
				},
				"type":"block"
			},
			{
				"pos":{
					"r":0,
					"x":0,
					"y":5
				},
				"type":"block"
			},
			{
				"pos":{
					"r":0,
					"x":-2,
					"y":-5
				},
				"type":"block"
			},
			{
				"pos":{
					"r":0,
					"x":1,
					"y":-5
				},
				"type":"block"
			},
			{
				"pos":{
					"r":0,
					"x":-2,
					"y":-6
				},
				"type":"block"
			},
			{
				"pos":{
					"r":0,
					"x":0,
					"y":-6
				},
				"type":"block"
			},
			{
				"pos":{
					"r":0,
					"x":1,
					"y":-6
				},
				"type":"block"
			},
			{
				"item":"CbCrCyCg",
				"pos":{
					"r":0,
					"x":-1,
					"y":-6
				},
				"type":"goal"
			}
		],
		"bounds":{
			"w":4,
			"h":12
		},
		"version":1,
		"excludedBuildings":[
			"rotater",
			"trash",
			"belt"
		]
	},
	"meta":{
		"difficulty":0.17391304347826086,
		"averageTime":94.76315789473684,
		"downloads":46,
		"shortKey":"CbCrCyCg",
		"author":"player#363082282",
		"completions":38,
		"id":4145,
		"completed":false,
		"title":"QWQ     QWQ",
		"likes":9
	}
}
