{
	"game":{
		"buildings":[
			{
				"item":"SbSgWrCw",
				"pos":{
					"r":0,
					"x":-1,
					"y":1
				},
				"type":"emitter"
			},
			{
				"item":"WrCwSbSg",
				"pos":{
					"r":0,
					"x":-1,
					"y":-3
				},
				"type":"goal"
			},
			{
				"pos":{
					"r":0,
					"x":0,
					"y":1
				},
				"type":"block"
			},
			{
				"pos":{
					"r":0,
					"x":0,
					"y":-3
				},
				"type":"block"
			}
		],
		"bounds":{
			"w":2,
			"h":5
		},
		"version":1,
		"excludedBuildings":[
			
		]
	},
	"meta":{
		"difficulty":0.11111111111111116,
		"averageTime":21.291666666666668,
		"downloads":27,
		"shortKey":"SbSgWrCw",
		"author":"player#628657621",
		"completions":24,
		"id":4550,
		"completed":false,
		"title":"Squeeze",
		"likes":3
	}
}
