{
	"game":{
		"buildings":[
			{
				"item":"CrCrCrCr",
				"pos":{
					"r":90,
					"x":-7,
					"y":5
				},
				"type":"emitter"
			},
			{
				"item":"CgCgCgCg",
				"pos":{
					"r":180,
					"x":5,
					"y":-4
				},
				"type":"emitter"
			},
			{
				"item":"CbCbCbCb",
				"pos":{
					"r":270,
					"x":1,
					"y":5
				},
				"type":"emitter"
			},
			{
				"item":"CyCyCyCy",
				"pos":{
					"r":270,
					"x":4,
					"y":4
				},
				"type":"emitter"
			},
			{
				"item":"CpCpCpCp",
				"pos":{
					"r":0,
					"x":0,
					"y":-7
				},
				"type":"emitter"
			},
			{
				"item":"CcCcCcCc",
				"pos":{
					"r":0,
					"x":-7,
					"y":-1
				},
				"type":"emitter"
			},
			{
				"item":"CwCwCwCw",
				"pos":{
					"r":90,
					"x":5,
					"y":2
				},
				"type":"emitter"
			},
			{
				"item":"SrSrSrSr",
				"pos":{
					"r":0,
					"x":-2,
					"y":0
				},
				"type":"emitter"
			},
			{
				"item":"SgSgSgSg",
				"pos":{
					"r":90,
					"x":-6,
					"y":1
				},
				"type":"emitter"
			},
			{
				"item":"CrCrCrCr",
				"pos":{
					"r":90,
					"x":4,
					"y":-6
				},
				"type":"goal"
			},
			{
				"item":"CyCyCyCy",
				"pos":{
					"r":270,
					"x":-6,
					"y":-6
				},
				"type":"goal"
			},
			{
				"item":"SrSrSrSr",
				"pos":{
					"r":90,
					"x":-3,
					"y":-5
				},
				"type":"goal"
			},
			{
				"item":"CwCwCwCw",
				"pos":{
					"r":0,
					"x":-3,
					"y":-2
				},
				"type":"goal"
			},
			{
				"item":"SgSgSgSg",
				"pos":{
					"r":90,
					"x":1,
					"y":-4
				},
				"type":"goal"
			},
			{
				"item":"CbCbCbCb",
				"pos":{
					"r":0,
					"x":3,
					"y":-3
				},
				"type":"goal"
			},
			{
				"item":"CgCgCgCg",
				"pos":{
					"r":0,
					"x":0,
					"y":3
				},
				"type":"goal"
			},
			{
				"item":"CcCcCcCc",
				"pos":{
					"r":270,
					"x":3,
					"y":1
				},
				"type":"goal"
			},
			{
				"item":"CpCpCpCp",
				"pos":{
					"r":90,
					"x":-4,
					"y":3
				},
				"type":"goal"
			}
		],
		"bounds":{
			"w":15,
			"h":15
		},
		"version":1,
		"excludedBuildings":[
			"balancer",
			"cutter",
			"rotater",
			"stacker",
			"mixer",
			"painter",
			"trash",
			"underground_belt"
		]
	},
	"meta":{
		"difficulty":0.5,
		"averageTime":449.09090909090907,
		"downloads":46,
		"shortKey":"--CpRrCp:SwSwScSc",
		"author":"player#664581247",
		"completions":22,
		"id":5144,
		"completed":true,
		"title":"Connect",
		"likes":12
	}
}
