{
	"game":{
		"buildings":[
			{
				"item":"red",
				"pos":{
					"r":0,
					"x":-1,
					"y":2
				},
				"type":"emitter"
			},
			{
				"item":"CuCuCuCu",
				"pos":{
					"r":270,
					"x":1,
					"y":1
				},
				"type":"emitter"
			},
			{
				"item":"RuRuRuRu",
				"pos":{
					"r":270,
					"x":1,
					"y":0
				},
				"type":"emitter"
			},
			{
				"item":"RrRrRrRr:CrCrCrCr",
				"pos":{
					"r":0,
					"x":-3,
					"y":-3
				},
				"type":"goal"
			},
			{
				"item":"RrRrRrRr:CrCrCrCr",
				"pos":{
					"r":0,
					"x":-2,
					"y":-3
				},
				"type":"goal"
			}
		],
		"bounds":{
			"w":8,
			"h":6
		},
		"version":1,
		"excludedBuildings":[
			
		]
	},
	"meta":{
		"difficulty":0.06521739130434778,
		"averageTime":86.03100775193798,
		"downloads":138,
		"shortKey":"RpSuRpCb:RbRpRbSp",
		"author":"Olivier",
		"completions":129,
		"id":5336,
		"completed":false,
		"title":"TFTFRF",
		"likes":23
	}
}
