{
	"game":{
		"buildings":[
			{
				"item":"SgSgSgSg:CgCgCgCg",
				"pos":{
					"r":90,
					"x":-8,
					"y":-1
				},
				"type":"emitter"
			},
			{
				"item":"CwRyRyCw:Cu----Cu",
				"pos":{
					"r":90,
					"x":-8,
					"y":-2
				},
				"type":"emitter"
			},
			{
				"item":"uncolored",
				"pos":{
					"r":90,
					"x":-8,
					"y":-3
				},
				"type":"emitter"
			},
			{
				"pos":{
					"r":0,
					"x":-5,
					"y":1
				},
				"type":"block"
			},
			{
				"pos":{
					"r":0,
					"x":-5,
					"y":-3
				},
				"type":"block"
			},
			{
				"pos":{
					"r":0,
					"x":-4,
					"y":-3
				},
				"type":"block"
			},
			{
				"pos":{
					"r":0,
					"x":-4,
					"y":1
				},
				"type":"block"
			},
			{
				"pos":{
					"r":0,
					"x":-3,
					"y":1
				},
				"type":"block"
			},
			{
				"pos":{
					"r":0,
					"x":-3,
					"y":-3
				},
				"type":"block"
			},
			{
				"pos":{
					"r":0,
					"x":-2,
					"y":-3
				},
				"type":"block"
			},
			{
				"pos":{
					"r":0,
					"x":-2,
					"y":-2
				},
				"type":"block"
			},
			{
				"pos":{
					"r":0,
					"x":-2,
					"y":0
				},
				"type":"block"
			},
			{
				"pos":{
					"r":0,
					"x":-2,
					"y":1
				},
				"type":"block"
			},
			{
				"pos":{
					"r":0,
					"x":-1,
					"y":1
				},
				"type":"block"
			},
			{
				"pos":{
					"r":0,
					"x":-1,
					"y":0
				},
				"type":"block"
			},
			{
				"pos":{
					"r":0,
					"x":0,
					"y":0
				},
				"type":"block"
			},
			{
				"pos":{
					"r":0,
					"x":0,
					"y":1
				},
				"type":"block"
			},
			{
				"pos":{
					"r":0,
					"x":-1,
					"y":-2
				},
				"type":"block"
			},
			{
				"pos":{
					"r":0,
					"x":1,
					"y":0
				},
				"type":"block"
			},
			{
				"pos":{
					"r":0,
					"x":1,
					"y":1
				},
				"type":"block"
			},
			{
				"pos":{
					"r":0,
					"x":0,
					"y":-2
				},
				"type":"block"
			},
			{
				"pos":{
					"r":0,
					"x":1,
					"y":-2
				},
				"type":"block"
			},
			{
				"pos":{
					"r":0,
					"x":2,
					"y":-2
				},
				"type":"block"
			},
			{
				"pos":{
					"r":0,
					"x":2,
					"y":0
				},
				"type":"block"
			},
			{
				"pos":{
					"r":0,
					"x":2,
					"y":1
				},
				"type":"block"
			},
			{
				"pos":{
					"r":0,
					"x":7,
					"y":1
				},
				"type":"block"
			},
			{
				"pos":{
					"r":0,
					"x":7,
					"y":0
				},
				"type":"block"
			},
			{
				"pos":{
					"r":0,
					"x":7,
					"y":-1
				},
				"type":"block"
			},
			{
				"pos":{
					"r":0,
					"x":7,
					"y":-2
				},
				"type":"block"
			},
			{
				"pos":{
					"r":0,
					"x":7,
					"y":-3
				},
				"type":"block"
			},
			{
				"item":"RuRuRuRu:SuSuSuSu:CuCuCuCu:CwRyRyCw",
				"pos":{
					"r":180,
					"x":6,
					"y":1
				},
				"type":"goal"
			},
			{
				"pos":{
					"r":0,
					"x":5,
					"y":1
				},
				"type":"block"
			},
			{
				"pos":{
					"r":0,
					"x":5,
					"y":0
				},
				"type":"block"
			},
			{
				"pos":{
					"r":0,
					"x":6,
					"y":-3
				},
				"type":"block"
			},
			{
				"pos":{
					"r":0,
					"x":5,
					"y":-3
				},
				"type":"block"
			},
			{
				"item":"RuRuRuRu",
				"pos":{
					"r":90,
					"x":-1,
					"y":-3
				},
				"type":"emitter"
			},
			{
				"pos":{
					"r":0,
					"x":1,
					"y":-3
				},
				"type":"block"
			},
			{
				"pos":{
					"r":0,
					"x":2,
					"y":-3
				},
				"type":"block"
			},
			{
				"pos":{
					"r":0,
					"x":3,
					"y":-2
				},
				"type":"block"
			},
			{
				"pos":{
					"r":0,
					"x":3,
					"y":0
				},
				"type":"block"
			},
			{
				"pos":{
					"r":0,
					"x":4,
					"y":0
				},
				"type":"block"
			},
			{
				"pos":{
					"r":0,
					"x":3,
					"y":1
				},
				"type":"block"
			},
			{
				"pos":{
					"r":0,
					"x":4,
					"y":1
				},
				"type":"block"
			}
		],
		"bounds":{
			"w":16,
			"h":5
		},
		"version":1,
		"excludedBuildings":[
			
		]
	},
	"meta":{
		"difficulty":0.375,
		"averageTime":411.8,
		"downloads":17,
		"shortKey":"RuRuRuRu:SuSuSuSu:CuCuCuCu:CwRyRyCw",
		"author":"MaximusWhitimus",
		"completions":10,
		"id":8444,
		"completed":false,
		"title":"Safe Stowage",
		"likes":1
	}
}
