{
	"game":{
		"buildings":[
			{
				"pos":{
					"r":0,
					"x":-4,
					"y":0
				},
				"type":"block"
			},
			{
				"pos":{
					"r":0,
					"x":-4,
					"y":1
				},
				"type":"block"
			},
			{
				"item":"WuWuWuWu",
				"pos":{
					"r":270,
					"x":-3,
					"y":-2
				},
				"type":"emitter"
			},
			{
				"pos":{
					"r":0,
					"x":-3,
					"y":1
				},
				"type":"block"
			},
			{
				"pos":{
					"r":0,
					"x":1,
					"y":1
				},
				"type":"block"
			},
			{
				"item":"----WuWu:Wu----Wu:Wu----Wu:----WuWu",
				"pos":{
					"r":180,
					"x":2,
					"y":1
				},
				"type":"goal"
			},
			{
				"pos":{
					"r":0,
					"x":3,
					"y":1
				},
				"type":"block"
			}
		],
		"bounds":{
			"w":8,
			"h":4
		},
		"version":1,
		"excludedBuildings":[
			
		]
	},
	"meta":{
		"downloads":6,
		"shortKey":"----WuWu:Wu----Wu:Wu----Wu:----WuWu",
		"author":"player#475489576",
		"completions":1,
		"id":2197,
		"completed":false,
		"title":"Cut_Rotate",
		"likes":0
	}
}
