{
	"game":{
		"buildings":[
			{
				"item":"red",
				"pos":{
					"r":0,
					"x":-2,
					"y":5
				},
				"type":"emitter"
			},
			{
				"item":"green",
				"pos":{
					"r":0,
					"x":-1,
					"y":5
				},
				"type":"emitter"
			},
			{
				"item":"blue",
				"pos":{
					"r":0,
					"x":0,
					"y":5
				},
				"type":"emitter"
			},
			{
				"pos":{
					"r":0,
					"x":0,
					"y":2
				},
				"type":"block"
			},
			{
				"item":"WuWuWuWu",
				"pos":{
					"r":270,
					"x":0,
					"y":1
				},
				"type":"emitter"
			},
			{
				"pos":{
					"r":0,
					"x":0,
					"y":0
				},
				"type":"block"
			},
			{
				"pos":{
					"r":0,
					"x":0,
					"y":-1
				},
				"type":"block"
			},
			{
				"pos":{
					"r":0,
					"x":-2,
					"y":-2
				},
				"type":"block"
			},
			{
				"pos":{
					"r":0,
					"x":-2,
					"y":-3
				},
				"type":"block"
			},
			{
				"item":"WwWw----",
				"pos":{
					"r":0,
					"x":-2,
					"y":-6
				},
				"type":"goal"
			},
			{
				"item":"WwWw----",
				"pos":{
					"r":0,
					"x":-1,
					"y":-6
				},
				"type":"goal"
			},
			{
				"item":"WwWw----",
				"pos":{
					"r":270,
					"x":-2,
					"y":-4
				},
				"type":"goal"
			},
			{
				"item":"WwWw----",
				"pos":{
					"r":0,
					"x":0,
					"y":-3
				},
				"type":"goal"
			},
			{
				"pos":{
					"r":0,
					"x":0,
					"y":-6
				},
				"type":"block"
			},
			{
				"pos":{
					"r":0,
					"x":0,
					"y":-5
				},
				"type":"block"
			},
			{
				"pos":{
					"r":0,
					"x":0,
					"y":-4
				},
				"type":"block"
			}
		],
		"bounds":{
			"w":3,
			"h":12
		},
		"version":1,
		"excludedBuildings":[
			"underground_belt"
		]
	},
	"meta":{
		"difficulty":0.049180327868852514,
		"averageTime":81.36206896551724,
		"downloads":183,
		"shortKey":"RrRrRrRr:SyCySyCy",
		"author":"dan.gimmler",
		"completions":174,
		"id":4761,
		"completed":false,
		"title":"Whiteeeeeee",
		"likes":32
	}
}
