{
	"game":{
		"buildings":[
			{
				"item":"SuSuSuSu",
				"pos":{
					"r":90,
					"x":-3,
					"y":-1
				},
				"type":"emitter"
			},
			{
				"item":"blue",
				"pos":{
					"r":90,
					"x":-3,
					"y":0
				},
				"type":"emitter"
			},
			{
				"item":"------Sb:------Sb:------Sb:------Sb",
				"pos":{
					"r":90,
					"x":-1,
					"y":-3
				},
				"type":"goal"
			},
			{
				"item":"Sb------:Sb------:Sb------:Sb------",
				"pos":{
					"r":90,
					"x":-1,
					"y":-2
				},
				"type":"goal"
			},
			{
				"pos":{
					"r":0,
					"x":1,
					"y":-3
				},
				"type":"block"
			},
			{
				"pos":{
					"r":0,
					"x":0,
					"y":-3
				},
				"type":"block"
			},
			{
				"pos":{
					"r":0,
					"x":0,
					"y":-2
				},
				"type":"block"
			},
			{
				"pos":{
					"r":0,
					"x":1,
					"y":-2
				},
				"type":"block"
			}
		],
		"bounds":{
			"w":5,
			"h":6
		},
		"version":1,
		"excludedBuildings":[
			
		]
	},
	"meta":{
		"difficulty":0.35064935064935066,
		"averageTime":234.06,
		"downloads":77,
		"shortKey":"------Sb:------Sb:------Sb:------Sb",
		"author":"A_Person",
		"completions":50,
		"id":4857,
		"completed":true,
		"title":"Compaction",
		"likes":19
	}
}
