{
	"game":{
		"buildings":[
			{
				"item":"CwCw--Cw:--Cw--Cw:--Cw--Cw:CwCw--Cw",
				"pos":{
					"r":0,
					"x":-3,
					"y":-6
				},
				"type":"goal"
			},
			{
				"item":"CwCwCwCw",
				"pos":{
					"r":0,
					"x":-3,
					"y":4
				},
				"type":"emitter"
			},
			{
				"pos":{
					"r":0,
					"x":-2,
					"y":4
				},
				"type":"block"
			},
			{
				"pos":{
					"r":0,
					"x":-1,
					"y":4
				},
				"type":"block"
			},
			{
				"pos":{
					"r":0,
					"x":0,
					"y":4
				},
				"type":"block"
			},
			{
				"pos":{
					"r":0,
					"x":1,
					"y":4
				},
				"type":"block"
			},
			{
				"pos":{
					"r":0,
					"x":1,
					"y":3
				},
				"type":"block"
			},
			{
				"pos":{
					"r":0,
					"x":1,
					"y":2
				},
				"type":"block"
			},
			{
				"pos":{
					"r":0,
					"x":1,
					"y":1
				},
				"type":"block"
			},
			{
				"pos":{
					"r":0,
					"x":1,
					"y":0
				},
				"type":"block"
			},
			{
				"pos":{
					"r":0,
					"x":1,
					"y":-1
				},
				"type":"block"
			},
			{
				"pos":{
					"r":0,
					"x":1,
					"y":-2
				},
				"type":"block"
			},
			{
				"pos":{
					"r":0,
					"x":1,
					"y":-3
				},
				"type":"block"
			},
			{
				"pos":{
					"r":0,
					"x":0,
					"y":-4
				},
				"type":"block"
			},
			{
				"pos":{
					"r":0,
					"x":1,
					"y":-4
				},
				"type":"block"
			},
			{
				"pos":{
					"r":0,
					"x":1,
					"y":-5
				},
				"type":"block"
			},
			{
				"pos":{
					"r":0,
					"x":1,
					"y":-6
				},
				"type":"block"
			},
			{
				"pos":{
					"r":0,
					"x":0,
					"y":-6
				},
				"type":"block"
			},
			{
				"pos":{
					"r":0,
					"x":-1,
					"y":-6
				},
				"type":"block"
			},
			{
				"pos":{
					"r":0,
					"x":-2,
					"y":-6
				},
				"type":"block"
			},
			{
				"pos":{
					"r":0,
					"x":0,
					"y":-5
				},
				"type":"block"
			},
			{
				"pos":{
					"r":0,
					"x":-1,
					"y":-5
				},
				"type":"block"
			}
		],
		"bounds":{
			"w":5,
			"h":11
		},
		"version":1,
		"excludedBuildings":[
			
		]
	},
	"meta":{
		"downloads":19,
		"shortKey":"CwCw--Cw:--Cw--Cw:--Cw--Cw:CwCw--Cw",
		"author":"player#257456487",
		"completions":0,
		"id":6247,
		"completed":false,
		"title":"KALA34",
		"likes":0
	}
}
