{
	"game":{
		"buildings":[
			{
				"item":"Cr----Cr",
				"pos":{
					"r":90,
					"x":-4,
					"y":2
				},
				"type":"emitter"
			},
			{
				"item":"Cy----Cy",
				"pos":{
					"r":90,
					"x":-4,
					"y":1
				},
				"type":"emitter"
			},
			{
				"item":"Cg----Cg",
				"pos":{
					"r":90,
					"x":-4,
					"y":-2
				},
				"type":"emitter"
			},
			{
				"item":"Cc----Cc",
				"pos":{
					"r":90,
					"x":-4,
					"y":-3
				},
				"type":"emitter"
			},
			{
				"item":"--RwRw--",
				"pos":{
					"r":90,
					"x":0,
					"y":0
				},
				"type":"emitter"
			},
			{
				"item":"CcRwRwCc:Cg----Cg:Cy----Cy:Cr----Cr",
				"pos":{
					"r":90,
					"x":2,
					"y":-1
				},
				"type":"goal"
			},
			{
				"pos":{
					"r":0,
					"x":-1,
					"y":1
				},
				"type":"block"
			},
			{
				"pos":{
					"r":0,
					"x":-1,
					"y":2
				},
				"type":"block"
			},
			{
				"pos":{
					"r":0,
					"x":-2,
					"y":2
				},
				"type":"block"
			},
			{
				"pos":{
					"r":0,
					"x":0,
					"y":1
				},
				"type":"block"
			},
			{
				"pos":{
					"r":0,
					"x":0,
					"y":2
				},
				"type":"block"
			},
			{
				"pos":{
					"r":0,
					"x":1,
					"y":2
				},
				"type":"block"
			},
			{
				"pos":{
					"r":0,
					"x":1,
					"y":1
				},
				"type":"block"
			},
			{
				"pos":{
					"r":0,
					"x":2,
					"y":1
				},
				"type":"block"
			},
			{
				"pos":{
					"r":0,
					"x":2,
					"y":2
				},
				"type":"block"
			},
			{
				"pos":{
					"r":0,
					"x":2,
					"y":0
				},
				"type":"block"
			},
			{
				"pos":{
					"r":0,
					"x":2,
					"y":-2
				},
				"type":"block"
			},
			{
				"pos":{
					"r":0,
					"x":1,
					"y":-2
				},
				"type":"block"
			},
			{
				"pos":{
					"r":0,
					"x":0,
					"y":-2
				},
				"type":"block"
			},
			{
				"pos":{
					"r":0,
					"x":-1,
					"y":-2
				},
				"type":"block"
			},
			{
				"pos":{
					"r":0,
					"x":-1,
					"y":-3
				},
				"type":"block"
			},
			{
				"pos":{
					"r":0,
					"x":0,
					"y":-3
				},
				"type":"block"
			},
			{
				"pos":{
					"r":0,
					"x":1,
					"y":-3
				},
				"type":"block"
			},
			{
				"pos":{
					"r":0,
					"x":2,
					"y":-3
				},
				"type":"block"
			},
			{
				"pos":{
					"r":0,
					"x":-3,
					"y":-1
				},
				"type":"block"
			},
			{
				"pos":{
					"r":0,
					"x":-3,
					"y":0
				},
				"type":"block"
			},
			{
				"pos":{
					"r":0,
					"x":-4,
					"y":0
				},
				"type":"block"
			},
			{
				"pos":{
					"r":0,
					"x":-4,
					"y":-1
				},
				"type":"block"
			}
		],
		"bounds":{
			"w":7,
			"h":6
		},
		"version":1,
		"excludedBuildings":[
			
		]
	},
	"meta":{
		"difficulty":0.09999999999999998,
		"averageTime":23.166666666666668,
		"downloads":21,
		"shortKey":"CcRwRwCc:Cg----Cg:Cy----Cy:Cr----Cr",
		"author":"Inspector_2211",
		"completions":18,
		"id":6833,
		"completed":false,
		"title":"ice cream",
		"likes":3
	}
}
