{
	"game":{
		"buildings":[
			{
				"item":"Cw----Cw",
				"pos":{
					"r":90,
					"x":-5,
					"y":-2
				},
				"type":"emitter"
			},
			{
				"item":"Cw----Cw",
				"pos":{
					"r":90,
					"x":-6,
					"y":0
				},
				"type":"emitter"
			},
			{
				"item":"Cw----Cw:----CwCw:Cw----Cw:----CwCw",
				"pos":{
					"r":90,
					"x":3,
					"y":-1
				},
				"type":"goal"
			},
			{
				"pos":{
					"r":0,
					"x":0,
					"y":1
				},
				"type":"block"
			},
			{
				"pos":{
					"r":0,
					"x":1,
					"y":1
				},
				"type":"block"
			},
			{
				"pos":{
					"r":0,
					"x":2,
					"y":1
				},
				"type":"block"
			},
			{
				"pos":{
					"r":0,
					"x":3,
					"y":1
				},
				"type":"block"
			},
			{
				"pos":{
					"r":0,
					"x":3,
					"y":0
				},
				"type":"block"
			},
			{
				"pos":{
					"r":0,
					"x":2,
					"y":-2
				},
				"type":"block"
			},
			{
				"pos":{
					"r":0,
					"x":3,
					"y":-2
				},
				"type":"block"
			},
			{
				"pos":{
					"r":0,
					"x":-6,
					"y":-2
				},
				"type":"block"
			},
			{
				"pos":{
					"r":0,
					"x":-6,
					"y":-1
				},
				"type":"block"
			},
			{
				"pos":{
					"r":0,
					"x":-6,
					"y":1
				},
				"type":"block"
			},
			{
				"pos":{
					"r":0,
					"x":-5,
					"y":-1
				},
				"type":"block"
			}
		],
		"bounds":{
			"w":11,
			"h":4
		},
		"version":1,
		"excludedBuildings":[
			
		]
	},
	"meta":{
		"downloads":7,
		"shortKey":"Cw----Cw:----CwCw:Cw----Cw:----CwCw",
		"author":"Sakuya_Ayin",
		"completions":3,
		"id":943,
		"completed":false,
		"title":"BAD IDEA",
		"likes":2
	}
}
