{
	"game":{
		"buildings":[
			{
				"item":"----Sy--",
				"pos":{
					"r":90,
					"x":5,
					"y":-8
				},
				"type":"goal"
			},
			{
				"item":"Sg------",
				"pos":{
					"r":90,
					"x":5,
					"y":-7
				},
				"type":"goal"
			},
			{
				"item":"------Rb",
				"pos":{
					"r":90,
					"x":5,
					"y":-6
				},
				"type":"goal"
			},
			{
				"item":"------Rg",
				"pos":{
					"r":90,
					"x":5,
					"y":-5
				},
				"type":"goal"
			},
			{
				"item":"--WyWy--",
				"pos":{
					"r":90,
					"x":5,
					"y":-4
				},
				"type":"goal"
			},
			{
				"item":"RpRp----",
				"pos":{
					"r":90,
					"x":5,
					"y":-3
				},
				"type":"goal"
			},
			{
				"item":"--WrWr--:CrCrCrCr",
				"pos":{
					"r":90,
					"x":5,
					"y":-2
				},
				"type":"goal"
			},
			{
				"item":"SwSw----",
				"pos":{
					"r":90,
					"x":5,
					"y":-1
				},
				"type":"goal"
			},
			{
				"item":"SuSuSuSu",
				"pos":{
					"r":0,
					"x":-3,
					"y":1
				},
				"type":"emitter"
			},
			{
				"item":"CuCuCuCu",
				"pos":{
					"r":0,
					"x":-4,
					"y":0
				},
				"type":"emitter"
			},
			{
				"item":"WuWuWuWu",
				"pos":{
					"r":90,
					"x":-6,
					"y":-5
				},
				"type":"emitter"
			},
			{
				"item":"RuRuRuRu",
				"pos":{
					"r":0,
					"x":-4,
					"y":-7
				},
				"type":"emitter"
			},
			{
				"item":"red",
				"pos":{
					"r":0,
					"x":-2,
					"y":7
				},
				"type":"emitter"
			},
			{
				"item":"green",
				"pos":{
					"r":0,
					"x":-1,
					"y":7
				},
				"type":"emitter"
			},
			{
				"item":"blue",
				"pos":{
					"r":0,
					"x":3,
					"y":7
				},
				"type":"emitter"
			},
			{
				"item":"yellow",
				"pos":{
					"r":90,
					"x":2,
					"y":2
				},
				"type":"emitter"
			},
			{
				"pos":{
					"r":90,
					"x":5,
					"y":0
				},
				"type":"block"
			},
			{
				"pos":{
					"r":90,
					"x":5,
					"y":1
				},
				"type":"block"
			},
			{
				"pos":{
					"r":90,
					"x":5,
					"y":2
				},
				"type":"block"
			},
			{
				"pos":{
					"r":90,
					"x":5,
					"y":3
				},
				"type":"block"
			},
			{
				"pos":{
					"r":90,
					"x":5,
					"y":4
				},
				"type":"block"
			},
			{
				"pos":{
					"r":90,
					"x":5,
					"y":5
				},
				"type":"block"
			},
			{
				"pos":{
					"r":90,
					"x":5,
					"y":6
				},
				"type":"block"
			},
			{
				"pos":{
					"r":90,
					"x":5,
					"y":7
				},
				"type":"block"
			},
			{
				"pos":{
					"r":90,
					"x":-6,
					"y":3
				},
				"type":"block"
			},
			{
				"pos":{
					"r":90,
					"x":-5,
					"y":3
				},
				"type":"block"
			},
			{
				"pos":{
					"r":90,
					"x":-4,
					"y":3
				},
				"type":"block"
			},
			{
				"pos":{
					"r":90,
					"x":-3,
					"y":3
				},
				"type":"block"
			},
			{
				"pos":{
					"r":90,
					"x":-3,
					"y":4
				},
				"type":"block"
			},
			{
				"pos":{
					"r":90,
					"x":-3,
					"y":5
				},
				"type":"block"
			},
			{
				"pos":{
					"r":90,
					"x":-3,
					"y":6
				},
				"type":"block"
			},
			{
				"pos":{
					"r":90,
					"x":-3,
					"y":7
				},
				"type":"block"
			},
			{
				"pos":{
					"r":90,
					"x":-4,
					"y":7
				},
				"type":"block"
			},
			{
				"pos":{
					"r":90,
					"x":-5,
					"y":7
				},
				"type":"block"
			},
			{
				"pos":{
					"r":90,
					"x":-6,
					"y":7
				},
				"type":"block"
			},
			{
				"pos":{
					"r":90,
					"x":-6,
					"y":6
				},
				"type":"block"
			},
			{
				"pos":{
					"r":90,
					"x":-6,
					"y":5
				},
				"type":"block"
			},
			{
				"pos":{
					"r":90,
					"x":-6,
					"y":4
				},
				"type":"block"
			},
			{
				"pos":{
					"r":90,
					"x":-5,
					"y":4
				},
				"type":"block"
			},
			{
				"pos":{
					"r":90,
					"x":-4,
					"y":4
				},
				"type":"block"
			},
			{
				"pos":{
					"r":90,
					"x":-4,
					"y":5
				},
				"type":"block"
			},
			{
				"pos":{
					"r":90,
					"x":-4,
					"y":6
				},
				"type":"block"
			},
			{
				"pos":{
					"r":90,
					"x":-5,
					"y":6
				},
				"type":"block"
			},
			{
				"pos":{
					"r":90,
					"x":-5,
					"y":5
				},
				"type":"block"
			},
			{
				"pos":{
					"r":90,
					"x":-6,
					"y":0
				},
				"type":"block"
			},
			{
				"pos":{
					"r":90,
					"x":-6,
					"y":1
				},
				"type":"block"
			},
			{
				"pos":{
					"r":90,
					"x":-6,
					"y":2
				},
				"type":"block"
			}
		],
		"bounds":{
			"w":12,
			"h":16
		},
		"version":1,
		"excludedBuildings":[]
	},
	"meta":{
		"downloads":10,
		"shortKey":"SgWyWyRb",
		"author":"BlaZe",
		"completions":1,
		"id":2332,
		"completed":false,
		"title":"Nightmare Painting",
		"likes":1
	}
}
