{
	"game":{
		"buildings":[
			{
				"item":"RuRuRuRu",
				"pos":{
					"r":90,
					"x":-4,
					"y":-3
				},
				"type":"emitter"
			},
			{
				"item":"yellow",
				"pos":{
					"r":180,
					"x":-2,
					"y":1
				},
				"type":"emitter"
			},
			{
				"item":"Ry--Ry--:Ry--Ry--:RwRwRwRw",
				"pos":{
					"r":0,
					"x":-2,
					"y":-2
				},
				"type":"goal"
			},
			{
				"item":"white",
				"pos":{
					"r":0,
					"x":-1,
					"y":-1
				},
				"type":"emitter"
			}
		],
		"bounds":{
			"w":8,
			"h":6
		},
		"version":1,
		"excludedBuildings":[
			"mixer",
			"underground_belt"
		]
	},
	"meta":{
		"difficulty":0.2987012987012987,
		"averageTime":305.3333333333333,
		"downloads":78,
		"shortKey":"Ry--Ry--:Ry--Ry--:RwRwRwRw",
		"author":"epicKieren66",
		"completions":54,
		"id":3112,
		"completed":true,
		"title":"Odd Circle",
		"likes":25
	}
}
